pacman/PACsettings.ini
pacman/PacMan.py
pacman/__init__.py
pacman/managers/IRHM.py
pacman/managers/PacMAN_LOGO_TRP.ico
pacman/managers/PycroCom.py
pacman/managers/SCM.py
pacman/managers/StageCommunicator_Template.py
pacman/managers/__init__.py
pacman/managers/pacmangui.py
pacman/managers/sliceViewer.py
pacman/utils/__init__.py
pacman/utils/utils.py
pacman/managers/PerPosScript.txt
pacman/managers/StartPosScript.txt
pacman_ipam-0.9.6.dist-info/METADATA
pacman_ipam-0.9.6.dist-info/WHEEL
pacman_ipam-0.9.6.dist-info/licenses/LICENSE
pacman_ipam-0.9.6.dist-info/RECORD
